<message message-id="18217504.1155055485761.JavaMail.jboss@colo-br-02.atl.jboss.com" list="org.jboss.lists.jboss-user" id="24acqhjgh4z7nue4" type="users" date="2006-08-08T12:44:45" year="2006-01-01" year-month="2006-08-01" year-month-day="2006-08-08" thread-id="24acqhjgh4z7nue4"><headers><envelope-from-line>From do-not-reply@jboss.com  Tue Aug  8 12:44:45 2006</envelope-from-line><from personal="kavlondon" address="do-not-reply@jboss.com">kavlondon &lt;do-not-reply@jboss.com&gt;</from><subject normal="[jboss-user] [Beginners Corner] - Please Help robot.createScreenCapture(rectangle); from J2EE">[jboss-user] [Beginners Corner] - Please Help robot.createScreenCapture(rectangle); from J2EE</subject><x-spam-checker-version>SpamAssassin 3.2.4 (2008-01-01) on
	spam-1.dev.markmail.int</x-spam-checker-version><x-spam-level/><x-spam-status>No, score=-1.8 required=5.0 tests=BAYES_00,INVALID_DATE,
	MISSING_HEADERS,NO_RECEIVED,NO_RELAYS autolearn=disabled version=3.2.4</x-spam-status><date>Mon Sep 17 12:56:32 2007</date><message-id>18217504.1155055485761.JavaMail.jboss@colo-br-02.atl.jboss.com</message-id><content-type>text/plain; charset=iso-8859-1</content-type><mime-version>1.0</mime-version></headers><normalized-references><normalized-message-id>18217504.1155055485761.JavaMail.jboss@colo-br-02.atl.jboss.com</normalized-message-id></normalized-references><body type="text/plain; charset=iso-8859-1"><para depth="0">
When running jboss from the standart bat file my application functions as<br/>expected, ie. takes a screen shot of the host mashine and writes it into the<br/>browser window, but when I run Jboss as a service:

</para><para depth="0">"JBossService.exe -install JBoss C:\AVPB\jdk1.5.0_04\jre\bin\server\jvm.dll<br/>-Xmx400m<br/>-Djava.class.path=C:\AVPB\jdk1.5.0_04\lib\tools.jar;C:\AVPB\jboss-4.0.3SP1\bin\run.jar<br/>-start org.jboss.Main -stop org.jboss.Main -method systemExit -out<br/>C:\AVPB\jboss-4.0.3SP1\stdout.log -err C:\AVPB\jboss-4.0.3SP1\stderr.log<br/>-current C:\AVPB\jboss-4.0.3SP1 -auto
sc start Jboss"

</para><para depth="0">It doesn't seem to function correctly, I don't see any errors but it returns<br/>solid black image  instead of a current screen shot.

</para><para depth="0">System.out.println("Display-"+GraphicsEnvironment.getLocalGraphicsEnvironment().getDefaultScreenDevice().toString());

</para><para depth="0">the above returns this: 

</para><para depth="0">Display-Win32GraphicsDevice[screen=1]

</para><para depth="0">Please somebody Help me ! :-) 

</para><para depth="0">View the original post :<br/><url>http://www.jboss.com/index.html?module=bb&amp;op=viewtopic&amp;p=3963861#3963861</url>

</para><para depth="0">Reply to the post :<br/><url>http://www.jboss.com/index.html?module=bb&amp;op=posting&amp;mode=reply&amp;p=3963861</url>

</para></body></message>