<message message-id="cjjg2o$dtf$1@sea.gmane.org" list="com.redhat.fedora-test-list" id="24bcg4spkabwamtf" type="development" date="2004-10-01T07:46:32-04:00" year="2004-01-01" year-month="2004-10-01" year-month-day="2004-10-01" thread-id="zgtw374qxgs6hfk3"><headers><envelope-from-line>From glrft-fedora-test-list@gmane.org Fri Oct  1 07:46:48 2004</envelope-from-line><from personal="Neal D. Becker" address="ndbecker2@verizon.net">"Neal D. Becker" &lt;ndbecker2@verizon.net&gt;</from><to personal="fedora-test-list@redhat.com" address="fedora-test-list@redhat.com">fedora-test-list@redhat.com</to><subject normal="gettext rpm defect">gettext rpm defect</subject><received>from int-mx1.corp.redhat.com (int-mx1.corp.redhat.com
	[172.16.52.254])
	by listman.util.phx.redhat.com (8.12.11/8.12.10) with ESMTP id
	i91BkmZi032760 for &lt;fedora-test-list@listman.util.phx.redhat.com&gt;;
	Fri, 1 Oct 2004 07:46:48 -0400</received><received>from mx3.redhat.com (mx3.redhat.com [172.16.48.32])
	by int-mx1.corp.redhat.com (8.11.6/8.11.6) with ESMTP id i91Bkmr02941
	for &lt;fedora-test-list@redhat.com&gt;; Fri, 1 Oct 2004 07:46:48 -0400</received><received>from main.gmane.org (main.gmane.org [80.91.229.2])
	by mx3.redhat.com (8.12.11/8.12.10) with ESMTP id i91Bkan8026253
	for &lt;fedora-test-list@redhat.com&gt;; Fri, 1 Oct 2004 07:46:41 -0400</received><received>from list by main.gmane.org with local (Exim 3.35 #1 (Debian))
	id 1CDLrv-0007J7-00
	for &lt;fedora-test-list@redhat.com&gt;; Fri, 01 Oct 2004 13:46:35 +0200</received><received>from 139.85.94.36 ([139.85.94.36])
	by main.gmane.org with esmtp (Gmexim 0.1 (Debian))
	id 1AlnuQ-0007hv-00
	for &lt;fedora-test-list@redhat.com&gt;; Fri, 01 Oct 2004 13:46:35 +0200</received><received>from ndbecker2 by 139.85.94.36 with local (Gmexim 0.1 (Debian))
	id 1AlnuQ-0007hv-00
	for &lt;fedora-test-list@redhat.com&gt;; Fri, 01 Oct 2004 13:46:35 +0200</received><x-injected-via-gmane>http://gmane.org/</x-injected-via-gmane><date>Fri, 01 Oct 2004 07:46:32 -0400</date><lines>4</lines><message-id>cjjg2o$dtf$1@sea.gmane.org</message-id><mime-version>1.0</mime-version><content-type>text/plain; charset=iso-8859-1</content-type><content-transfer-encoding>7Bit</content-transfer-encoding><x-complaints-to>usenet@sea.gmane.org</x-complaints-to><x-gmane-nntp-posting-host>139.85.94.36</x-gmane-nntp-posting-host><user-agent>KNode/0.8.0</user-agent><sender>news &lt;news@sea.gmane.org&gt;</sender><x-redhat-spam-score>0 </x-redhat-spam-score><x-loop>fedora-test-list@redhat.com</x-loop><x-beenthere>fedora-test-list@redhat.com</x-beenthere><x-mailman-version>2.1.5</x-mailman-version><precedence>junk</precedence><reply-to>For testers of Fedora Core development releases
	&lt;fedora-test-list@redhat.com&gt;</reply-to><list-id>For testers of Fedora Core development releases
	&lt;fedora-test-list.redhat.com&gt;</list-id><list-unsubscribe>&lt;http://www.redhat.com/mailman/listinfo/fedora-test-list&gt;,
	&lt;mailto:fedora-test-list-request@redhat.com?subject=unsubscribe&gt;</list-unsubscribe><list-archive>&lt;/archives/fedora-test-list&gt;</list-archive><list-post>&lt;mailto:fedora-test-list@redhat.com&gt;</list-post><list-help>&lt;mailto:fedora-test-list-request@redhat.com?subject=help&gt;</list-help><list-subscribe>&lt;http://www.redhat.com/mailman/listinfo/fedora-test-list&gt;,
	&lt;mailto:fedora-test-list-request@redhat.com?subject=subscribe&gt;</list-subscribe><x-list-received-date>Fri, 01 Oct 2004 11:46:49 -0000</x-list-received-date></headers><normalized-references><normalized-message-id>cjjg2o$dtf$1@sea.gmane.org</normalized-message-id></normalized-references><body type="text/plain; charset=iso-8859-1"><para depth="0">gettext 100 % done 30/572
/var/tmp/rpm/rpm-tmp.63051: line 2: fg: no job control
error: %post(gettext-0.14.1-9) scriptlet failed, exit status 1
</para></body></message>