<message message-id="1e8ba6fb0911231205q6ea44bf4gdec3de67187e839b@mail.gmail.com" list="com.ubuntu.lists.ubuntu-gt" id="24bd55qeaybebbp3" type="general" date="2009-11-23T14:05:35-06:00" year="2009-01-01" year-month="2009-11-01" year-month-day="2009-11-23" thread-id="24bd55qeaybebbp3"><headers><envelope-from-line>From juliorcb@gmail.com Mon Nov 23 20:05:38 2009</envelope-from-line><from personal="Julio Colindres" address="juliorcb@gmail.com">Julio Colindres &lt;juliorcb@gmail.com&gt;</from><to personal="Ubuntu Guatemala" address="ubuntu-gt@lists.ubuntu.com">Ubuntu Guatemala &lt;ubuntu-gt@lists.ubuntu.com&gt;</to><subject normal="[ubuntu-gt] Duda: se podrá personalizar los emblemas">[ubuntu-gt] Duda: se podrá personalizar los emblemas</subject><received>from mail-yx0-f172.google.com ([209.85.210.172])
	by chlorine.canonical.com with esmtp (Exim 4.60)
	(envelope-from &lt;juliorcb@gmail.com&gt;) id 1NCfAG-0002si-Cl
	for ubuntu-gt@lists.ubuntu.com; Mon, 23 Nov 2009 20:05:37 +0000</received><received>by yxe2 with SMTP id 2so2356766yxe.18
	for &lt;ubuntu-gt@lists.ubuntu.com&gt;; Mon, 23 Nov 2009 12:05:35 -0800 (PST)</received><mime-version>1.0</mime-version><received>by 10.150.244.4 with SMTP id r4mr9328524ybh.127.1259006735634; Mon, 
	23 Nov 2009 12:05:35 -0800 (PST)</received><date>Mon, 23 Nov 2009 14:05:35 -0600</date><message-id>1e8ba6fb0911231205q6ea44bf4gdec3de67187e839b@mail.gmail.com</message-id><content-type>multipart/alternative; boundary=000e0cd25d143f52f404790f5975</content-type><x-beenthere>ubuntu-gt@lists.ubuntu.com</x-beenthere><x-mailman-version>2.1.8</x-mailman-version><precedence>list</precedence><reply-to>Ubuntu Guatemala &lt;ubuntu-gt@lists.ubuntu.com&gt;</reply-to><list-id>Ubuntu Guatemala &lt;ubuntu-gt.lists.ubuntu.com&gt;</list-id><list-unsubscribe>&lt;https://lists.ubuntu.com/mailman/listinfo/ubuntu-gt&gt;,
	&lt;mailto:ubuntu-gt-request@lists.ubuntu.com?subject=unsubscribe&gt;</list-unsubscribe><list-archive>&lt;https://lists.ubuntu.com/archives/ubuntu-gt&gt;</list-archive><list-post>&lt;mailto:ubuntu-gt@lists.ubuntu.com&gt;</list-post><list-help>&lt;mailto:ubuntu-gt-request@lists.ubuntu.com?subject=help&gt;</list-help><list-subscribe>&lt;https://lists.ubuntu.com/mailman/listinfo/ubuntu-gt&gt;,
	&lt;mailto:ubuntu-gt-request@lists.ubuntu.com?subject=subscribe&gt;</list-subscribe><x-list-received-date>Mon, 23 Nov 2009 20:05:38 -0000</x-list-received-date></headers><normalized-references><normalized-message-id>1e8ba6fb0911231205q6ea44bf4gdec3de67187e839b@mail.gmail.com</normalized-message-id></normalized-references><body multipart="multipart/alternative; boundary=000e0cd25d143f52f404790f5975" type="text/plain; charset=ISO-8859-1"><para depth="0">Me surge una duda, ustedes no saben si acaso es posible personalizar los
iconos que salen en la opción de emblemas. Me explico mejor, al darle clic
derecho a cualquier icono e ir a preferencias se abre un menú contextual que
tiene una pestañita de emblemas, los emblemas que tiene esta opción son los
que trae por default el ubuntu o bien los de los temas de iconos que uno
instale, pero mi pregunta es, habrá forma de agregar y quitar iconos a esa
opción, si alguien sabe me dice como porfas. Gracias.

</para><para depth="0">P.D. Talishte y JDardon, a ver si ahora si logro ver este mensaje?
</para></body></message>