<message message-id="2f244e850611291013n1dd99f65k8d8635cdcff2e6c4@mail.gmail.com" list="com.redhat.fedora-users-br" id="24bqcrw6pucqfaty" type="users" date="2006-11-29T15:13:50-03:00" year="2006-01-01" year-month="2006-11-01" year-month-day="2006-11-29" thread-id="nhwx6tls5od7j7ew"><headers><envelope-from-line>From acleber@gmail.com Wed Nov 29 13:13:55 2006</envelope-from-line><from personal="Alan Borim" address="acleber@gmail.com">Alan Borim &lt;acleber@gmail.com&gt;</from><to personal="Lista de discussão voltada para os usuários brasileiros do Fedora" address="fedora-users-br@redhat.com">=?ISO-8859-1?Q?Lista_de_discuss=E3o_voltada_para_?=
	=?ISO-8859-1?Q?os_usu=E1rios_brasileiros_do_Fedora?= &lt;fedora-users-br@redhat.com&gt;</to><subject normal="[Fedora-users-br] Como descobrir porta de aplicação">Re: [Fedora-users-br] Como descobrir porta de aplicação</subject><received>from int-mx1.corp.redhat.com (int-mx1.corp.redhat.com
	[172.16.52.254])
	by listman.util.phx.redhat.com (8.13.1/8.13.1) with ESMTP id
	kATIDtxo010157 for &lt;fedora-users-br@listman.util.phx.redhat.com&gt;;
	Wed, 29 Nov 2006 13:13:55 -0500</received><received>from mx3.redhat.com (mx3.redhat.com [172.16.48.32])
	by int-mx1.corp.redhat.com (8.13.1/8.13.1) with ESMTP id kATIDs9I016051
	for &lt;fedora-users-br@redhat.com&gt;; Wed, 29 Nov 2006 13:13:54 -0500</received><received>from ug-out-1314.google.com (ug-out-1314.google.com [66.249.92.170])
	by mx3.redhat.com (8.13.1/8.13.1) with ESMTP id kATIDpID013326
	for &lt;fedora-users-br@redhat.com&gt;; Wed, 29 Nov 2006 13:13:52 -0500</received><received>by ug-out-1314.google.com with SMTP id 30so1915305ugs
	for &lt;fedora-users-br@redhat.com&gt;; Wed, 29 Nov 2006 10:13:50 -0800 (PST)</received><domainkey-signature>a=rsa-sha1; q=dns; c=nofws; s=beta; d=gmail.com;
	h=received:message-id:date:from:to:subject:in-reply-to:mime-version:content-type:content-transfer-encoding:content-disposition:references;
	b=suUNSN6pYyoCPPMPkwlvQlwHG6y+IaVI/r/UiPCKIpFZs1omjfBP4sxZXq4MSV9D047gBbzVuwTJjIrLNljpfmOv3vKgIx2u7eXQsbuNEvGrWdJ5OnxtjW2TSOERrhlH0nlGVh//ofR53x7QR394xWdJaJP/BL2UeXwZAwY00Go=</domainkey-signature><received>by 10.78.160.2 with SMTP id i2mr2513328hue.1164824030227;
	Wed, 29 Nov 2006 10:13:50 -0800 (PST)</received><received>by 10.78.192.11 with HTTP; Wed, 29 Nov 2006 10:13:50 -0800 (PST)</received><message-id>2f244e850611291013n1dd99f65k8d8635cdcff2e6c4@mail.gmail.com</message-id><date>Wed, 29 Nov 2006 15:13:50 -0300</date><in-reply-to>&lt;7256ccd50611290952s32362e5eo44a00a9d4aa36fb7@mail.gmail.com&gt;</in-reply-to><mime-version>1.0</mime-version><content-type>text/plain; charset=iso-8859-1</content-type><content-disposition>inline</content-disposition><references>&lt;2f244e850611290822h650fc11cq7b597f5f8099a743@mail.gmail.com&gt;
	&lt;4089b1ea0611290839g641df95cwa2edc54869fd39c7@mail.gmail.com&gt;
	&lt;2f244e850611290841xcdb8334i245e9cdb40a05915@mail.gmail.com&gt;
	&lt;4f70c5c80611290934iba7efe7vb0a85494685b1b12@mail.gmail.com&gt;
	&lt;c5b571930611290938p52d77ef3od5d3a79984b5efde@mail.gmail.com&gt;
	&lt;2f244e850611290940s15a52eemd78b0999b778dfa6@mail.gmail.com&gt;
	&lt;7256ccd50611290952s32362e5eo44a00a9d4aa36fb7@mail.gmail.com&gt;</references><x-redhat-spam-score>0.103 </x-redhat-spam-score><content-transfer-encoding>8bit</content-transfer-encoding><x-mime-autoconverted>from quoted-printable to 8bit by
	listman.util.phx.redhat.com id kATIDtxo010157</x-mime-autoconverted><x-loop>fedora-users-br@redhat.com</x-loop><x-beenthere>fedora-users-br@redhat.com</x-beenthere><x-mailman-version>2.1.5</x-mailman-version><precedence>junk</precedence><reply-to>=?iso-8859-1?q?Lista_de_discuss=E3o_voltada_para_os_usu=E1rios_brasileiro?=
	=?iso-8859-1?q?s_do_Fedora?= &lt;fedora-users-br@redhat.com&gt;</reply-to><list-id>=?iso-8859-1?q?Lista_de_discuss=E3o_voltada_para_os_usu=E1rios_brasileiros_do_Fedora?=
	&lt;fedora-users-br.redhat.com&gt;</list-id><list-unsubscribe>&lt;https://www.redhat.com/mailman/listinfo/fedora-users-br&gt;,
	&lt;mailto:fedora-users-br-request@redhat.com?subject=unsubscribe&gt;</list-unsubscribe><list-archive>&lt;https://www.redhat.com/archives/fedora-users-br&gt;</list-archive><list-post>&lt;mailto:fedora-users-br@redhat.com&gt;</list-post><list-help>&lt;mailto:fedora-users-br-request@redhat.com?subject=help&gt;</list-help><list-subscribe>&lt;https://www.redhat.com/mailman/listinfo/fedora-users-br&gt;,
	&lt;mailto:fedora-users-br-request@redhat.com?subject=subscribe&gt;</list-subscribe><x-list-received-date>Wed, 29 Nov 2006 18:13:55 -0000</x-list-received-date></headers><normalized-references><normalized-message-id>2f244e850611291013n1dd99f65k8d8635cdcff2e6c4@mail.gmail.com</normalized-message-id><normalized-in-reply-to>7256ccd50611290952s32362e5eo44a00a9d4aa36fb7@mail.gmail.com</normalized-in-reply-to><normalized-reference>2f244e850611290822h650fc11cq7b597f5f8099a743@mail.gmail.com</normalized-reference><normalized-reference>4089b1ea0611290839g641df95cwa2edc54869fd39c7@mail.gmail.com</normalized-reference><normalized-reference>2f244e850611290841xcdb8334i245e9cdb40a05915@mail.gmail.com</normalized-reference><normalized-reference>4f70c5c80611290934iba7efe7vb0a85494685b1b12@mail.gmail.com</normalized-reference><normalized-reference>c5b571930611290938p52d77ef3od5d3a79984b5efde@mail.gmail.com</normalized-reference><normalized-reference>2f244e850611290940s15a52eemd78b0999b778dfa6@mail.gmail.com</normalized-reference><normalized-reference>7256ccd50611290952s32362e5eo44a00a9d4aa36fb7@mail.gmail.com</normalized-reference></normalized-references><body type="text/plain; charset=iso-8859-1"><para depth="0">hehehehe é verdade.

</para><para depth="0">Em 29/11/06, Rafael Gomes&lt;<email>rafael@gnufacs.org</email>&gt; escreveu:
</para><quote depth="1"><quotepara depth="1">Ou então usa o bom e velho tcpdump host &lt;ip de origem&gt;

</quotepara><quotepara depth="1">Outra coisa,

</quotepara><quotepara depth="1">Que programador foi esse que fez a aplicação sem especificação de porta? tsc
tsc tsc...

</quotepara><quotepara depth="1">2006/11/29, Alan Borim &lt; <email>acleber@gmail.com</email>&gt;:
</quotepara><quote depth="2"><quotepara depth="2">Putz cara é verdade..........

</quotepara><quotepara depth="2">Vou fazer essa modificação

</quotepara><quotepara depth="2">Valeu pela dica

</quotepara><quotepara depth="2">2006/11/29, Leonardo Korndorfer &lt;<email>leokorndorfer@gmail.com</email>&gt;:
</quotepara><quote depth="3"><quotepara depth="3">iptables -A INPUT -j LOG --log-prefix "iptablesIP"

</quotepara><quotepara depth="3">On 11/29/06, Felipe Tocchetto &lt;<email>felipe@tocchetto.com</email> &gt; wrote:
</quotepara><quote depth="4"><quotepara depth="4">O comportamento correto de seu firewall seria logar todos os pacotes
barrados por ele, através do log você conseguiria detectar.

</quotepara><quotepara depth="4">É como eu faço por aqui.

</quotepara><quotepara depth="4">2006/11/29, Alan Borim &lt;<email>acleber@gmail.com</email>&gt;:
</quotepara><quote depth="5"><quotepara depth="5">é uma aplicação desenvolvida em Java utilizando o Java RMI.

</quotepara><quotepara depth="5">Não é uma aplicação comum.

</quotepara><quotepara depth="5">Por isso que eu queria ver quais as portas que ele usa.

</quotepara><quotepara depth="5">2006/11/29, Edgar Gabaldi &lt; <email>edgabaldi@gmail.com</email> &gt;:
</quotepara><quote depth="6"><quotepara depth="6">Qual é o programa?

</quotepara><quotepara depth="6">2006/11/29, Alan Borim &lt; <email>acleber@gmail.com</email>&gt;:
</quotepara><quote depth="7"><quotepara depth="7">
Estou com um pequeno problema.

</quotepara><quotepara depth="7">Tenho uma aplicação funcionando na minha rede interna, mas
externamente o servidor não é localizado, por cauisa do
firewall.

</quotepara><quotepara depth="7">Então eu precisava saber as informações, Porta, IP, Protocolo e
tudo
mais que a aplicação usa pra poder liberar no firewall.

</quotepara><quotepara depth="7">Alguém sabe me informar qual é o comando, ou seqüência de que
</quotepara></quote></quote></quote></quote><quotepara depth="3">resolve
</quotepara><quote depth="4"><quote depth="5"><quote depth="6"><quotepara depth="6">isso??
</quotepara><quote depth="7"><quotepara depth="7">
Abraços.

</quotepara><quotepara depth="7">--
Alan Cleber

</quotepara></quote></quote></quote></quote></quote></quote><quotepara depth="1">------------------------------------------------------------------
</quotepara><quote depth="2"><quote depth="3"><quote depth="4"><quote depth="5"><quote depth="6"><quote depth="7"><quotepara depth="7">
</quotepara><quotepara depth="7">--
Fedora-users-br mailing list
<email>Fedora-users-br@redhat.com</email>

</quotepara></quote></quote></quote></quote><quotepara depth="3"><url>https://www.redhat.com/mailman/listinfo/fedora-users-br</url>
</quotepara><quote depth="4"><quote depth="5"><quote depth="6"><quote depth="7"><quotefooter type="noise" depth="7">
</quotefooter></quote><quotepara depth="6">--
Edgar Gabaldi
+ 55 92 9142-0780
edgabaldi at gmail dot com
Linux User: #434561
</quotepara><quotepara depth="6">--
Fedora-users-br mailing list
<email>Fedora-users-br@redhat.com</email>

</quotepara></quote></quote></quote><quotepara depth="3"><url>https://www.redhat.com/mailman/listinfo/fedora-users-br</url>
</quotepara><quote depth="4"><quote depth="5"><quote depth="6"><quotefooter type="noise" depth="6">
</quotefooter></quote><quotepara depth="5">--
Alan Cleber

</quotepara></quote></quote></quote></quote><quotepara depth="1">------------------------------------------------------------------
</quotepara><quote depth="2"><quote depth="3"><quote depth="4"><quote depth="5"><quotepara depth="5">www.alanborim.com.br
<email>alanborim@alanborim.com.br</email>

</quotepara></quote></quote></quote></quote><quotepara depth="1">------------------------------------------------------------------
</quotepara><quote depth="2"><quote depth="3"><quote depth="4"><quote depth="5"><quotepara depth="5">
</quotepara><quotepara depth="5">--
Fedora-users-br mailing list
<email>Fedora-users-br@redhat.com</email>

</quotepara></quote></quote></quote></quote><quotepara depth="1"><url>https://www.redhat.com/mailman/listinfo/fedora-users-br</url>
</quotepara><quote depth="2"><quote depth="3"><quote depth="4"><quote depth="5"><quotefooter type="noise" depth="5">
</quotefooter></quote><quotepara depth="4">--
Felipe L. Tocchetto
<url>http://felipe.tocchetto.com</url>

</quotepara><quotepara depth="4">--
Fedora-users-br mailing list
<email>Fedora-users-br@redhat.com</email>

</quotepara></quote></quote></quote><quotepara depth="1"><url>https://www.redhat.com/mailman/listinfo/fedora-users-br</url>
</quotepara><quote depth="2"><quote depth="3"><quote depth="4"><quotefooter type="noise" depth="4">
</quotefooter></quote><quotepara depth="3">--
Leonardo Korndorfer

</quotepara></quote></quote><quotepara depth="1">x50/x6F/x72/x20/x66/x61/x76/x6F/x72/x21/x20/x4E/x61/x6F/x20/x61/x63/x72/x65/x64/x69/x74/x6F/x20/x71/x75/x65/x20/x74/x75/x20/x74/x65/x20/x64/x65/x73/x74/x65/x20/x6F/x20/x74/x72/x61/x62/x61/x6C/x68/x6F/x20/x64/x65/x20/x74/x72/x61/x64/x75/x7A/x69/x72/x20/x69/x73/x73/x6F/x21/x20
</quotepara><quote depth="2"><quote depth="3"><quotepara depth="3">
alt.not.root.coffe.coffe.coffe

</quotepara><quotepara depth="3">A monk asked Joshu, "Does a dog have the Buddha nature?
Joshu retorted, "Mu!"

</quotepara><quotepara depth="3">MSN: <email>leokorndorfer@hotmail.com</email>
ICQ: 102788426
Slack + Gentoo
</quotepara><quotefooter type="list-management" depth="3">--
Fedora-users-br mailing list
<email>Fedora-users-br@redhat.com</email>
<url>https://www.redhat.com/mailman/listinfo/fedora-users-br</url>

</quotefooter></quote><quotepara depth="2">--
Alan Cleber

</quotepara></quote><quotepara depth="1">------------------------------------------------------------------
</quotepara><quote depth="2"><quotepara depth="2">www.alanborim.com.br
<email>alanborim@alanborim.com.br</email>

</quotepara></quote><quotepara depth="1">------------------------------------------------------------------
</quotepara><quote depth="2"><quotefooter type="noise" depth="2">
</quotefooter><quotefooter type="list-management" depth="2">--
Fedora-users-br mailing list
<email>Fedora-users-br@redhat.com</email>
<url>https://www.redhat.com/mailman/listinfo/fedora-users-br</url>

</quotefooter></quote><quotepara depth="1">--
Rafael Brito Gomes
Sistema de Informação
Universidade de Salvador (UNIFACS)

</quotepara><quotepara depth="1">Linux User - 430086

</quotepara><quotepara depth="1">O Tabareu - A Arte em sua forma mais Pura!
<url>http://tabareu.wordpress.com/</url>

</quotepara><quotepara depth="1">Blog do Sinot
<url>http://sinot.wordpress.com/</url>
</quotepara><quotefooter type="list-management" depth="1">--
Fedora-users-br mailing list
<email>Fedora-users-br@redhat.com</email>
<url>https://www.redhat.com/mailman/listinfo/fedora-users-br</url>

</quotefooter></quote><footer type="signature" depth="0" hash="6794502803285530814">-- 
Alan Cleber
</footer><para depth="0">------------------------------------------------------------------
www.alanborim.com.br
<email>alanborim@alanborim.com.br</email>
</para><footer type="noise" depth="0">------------------------------------------------------------------
</footer></body></message>