<message message-id="237292094.49078.1302529385845.JavaMail.tomcat@hel.zones.apache.org" list="org.apache.struts.issues" id="24bqtccyags7fsji" type="bugs" date="2011-04-11T13:43:05Z" year="2011-01-01" year-month="2011-04-01" year-month-day="2011-04-11" thread-id="2pm2lzh5orvbzmac"><headers><envelope-from-line>Mon Apr 11 05:43:45 2011</envelope-from-line><from personal="Philip Luppens (JIRA)" address="jira@apache.org">"Philip Luppens (JIRA)" &lt;jira@apache.org&gt;</from><to personal="issues@struts.apache.org" address="issues@struts.apache.org">issues@struts.apache.org</to><subject normal="[jira] [Resolved] (STR-3212) Exception in Mail Sending">[jira] [Resolved] (STR-3212) Exception in Mail Sending</subject><received>from srv-117c-be06.markmail.marklogic.com ([172.19.8.46])
          by mail-1.a.markmail.int (JAMES SMTP Server 2.3.1) with SMTP ID 469
          for &lt;johnie.conrad.holden@a.markmail.org&gt;;
          Mon, 11 Apr 2011 05:43:45 -0800 (GMT-08:00)</received><received>from mail.apache.org (slb-117n.markmail.marklogic.com [172.19.8.33])
	by mgw-1.public.markmail.int (Postfix) with SMTP id D1E4829081EA
	for &lt;johnie.conrad.holden@a.markmail.org&gt;; Mon, 11 Apr 2011 06:43:21 -0700 (PDT)</received><received>(qmail 62399 invoked by uid 500); 11 Apr 2011 13:43:44 -0000</received><mailing-list>contact issues-help@struts.apache.org; run by ezmlm</mailing-list><precedence>bulk</precedence><list-help>&lt;mailto:issues-help@struts.apache.org&gt;</list-help><list-unsubscribe>&lt;mailto:issues-unsubscribe@struts.apache.org&gt;</list-unsubscribe><list-post>&lt;mailto:issues@struts.apache.org&gt;</list-post><list-id>&lt;issues.struts.apache.org&gt;</list-id><reply-to>dev@struts.apache.org</reply-to><delivered-to>mailing list issues@struts.apache.org</delivered-to><received>(qmail 62392 invoked by uid 99); 11 Apr 2011 13:43:44 -0000</received><received>from athena.apache.org (HELO athena.apache.org) (140.211.11.136)
    by apache.org (qpsmtpd/0.29) with ESMTP; Mon, 11 Apr 2011 13:43:44 +0000</received><x-asf-spam-status>No, hits=-2000.0 required=5.0
	tests=ALL_TRUSTED,T_RP_MATCHES_RCVD</x-asf-spam-status><x-spam-check-by>apache.org</x-spam-check-by><received>from [140.211.11.116] (HELO hel.zones.apache.org) (140.211.11.116)
    by apache.org (qpsmtpd/0.29) with ESMTP; Mon, 11 Apr 2011 13:43:42 +0000</received><received>from hel.zones.apache.org (hel.zones.apache.org [140.211.11.116])
	by hel.zones.apache.org (Postfix) with ESMTP id CF4EA9C5A0
	for &lt;issues@struts.apache.org&gt;; Mon, 11 Apr 2011 13:43:05 +0000 (UTC)</received><date>Mon, 11 Apr 2011 13:43:05 +0000 (UTC)</date><message-id>237292094.49078.1302529385845.JavaMail.tomcat@hel.zones.apache.org</message-id><in-reply-to>&lt;2096271842.49069.1302528545918.JavaMail.tomcat@hel.zones.apache.org&gt;</in-reply-to><mime-version>1.0</mime-version><content-type>text/plain; charset=utf-8</content-type><content-transfer-encoding>7bit</content-transfer-encoding><x-jira-fingerprint>30527f35849b9dde25b450d4833f0394</x-jira-fingerprint></headers><normalized-references><normalized-message-id>237292094.49078.1302529385845.JavaMail.tomcat@hel.zones.apache.org</normalized-message-id><normalized-in-reply-to>2096271842.49069.1302528545918.JavaMail.tomcat@hel.zones.apache.org</normalized-in-reply-to></normalized-references><body type="text/plain; charset=utf-8"><para depth="0">
     [<br/><url>https://issues.apache.org/jira/browse/STR-3212?page=com.atlassian.jira.plugin.system.issuetabpanels:all-tabpanel</url><br/>]

</para><para depth="0">Philip Luppens resolved STR-3212.
</para><para depth="0">---------------------------------

</para><para depth="0">       Resolution: Not A Problem
    Fix Version/s:     (was: Pending Review)

</para><para depth="0">Read the error message.Your recipient's email address is invalid.

</para><quote depth="1"><quotepara depth="1">Exception in Mail Sending
</quotepara><quotepara depth="1">-------------------------

</quotepara><quotepara depth="1">                Key: STR-3212
                URL: <url>https://issues.apache.org/jira/browse/STR-3212</url>
            Project: Struts 1
         Issue Type: Bug
         Components: Website
   Affects Versions: 1.3.10
        Environment: Windows XP,J2SE 1.5 ,Eclipse Galelio IDE 
           Reporter: Umesh Annegirikar

</quotepara><quotepara depth="1">I am working on the healthcare peoject in which the new users are notified by<br/>email for their username and password
when user click on the register button All registration is OK but whenever<br/>clicking on the register button the
I have get the following Exception Stack whenever trying to send
http-8080-6 INFO  action.UserAction (UserAction.java:423) - MessagingException :<br/>Invalid Addresses
http-8080-6 ERROR utility.LogUtility (LogUtility.java:13) - rcptTo<br/>SMTPTransport.java 1835
http-8080-6 ERROR utility.LogUtility (LogUtility.java:14) -<br/>com.sun.mail.smtp.SMTPTransport.rcptTo(SMTPTransport.java:1835)
http-8080-6 ERROR utility.LogUtility (LogUtility.java:13) - sendMessage<br/>SMTPTransport.java 1098
http-8080-6 ERROR utility.LogUtility (LogUtility.java:14) -<br/>com.sun.mail.smtp.SMTPTransport.sendMessage(SMTPTransport.java:1098)
http-8080-6 ERROR utility.LogUtility (LogUtility.java:13) - send0<br/>Transport.java 195
http-8080-6 ERROR utility.LogUtility (LogUtility.java:14) -<br/>javax.mail.Transport.send0(Transport.java:195)
http-8080-6 ERROR utility.LogUtility (LogUtility.java:13) - send  Transport.java<br/>124
http-8080-6 ERROR utility.LogUtility (LogUtility.java:14) -<br/>javax.mail.Transport.send(Transport.java:124)
http-8080-6 ERROR utility.LogUtility (LogUtility.java:13) - postMail<br/>MailUtility.java 55
http-8080-6 ERROR utility.LogUtility (LogUtility.java:14) -<br/>com.udhc.utility.MailUtility.postMail(MailUtility.java:55)
http-8080-6 ERROR utility.LogUtility (LogUtility.java:13) - execute<br/>UserAction.java 419
http-8080-6 ERROR utility.LogUtility (LogUtility.java:14) -<br/>com.udhc.action.UserAction.execute(UserAction.java:419)
http-8080-6 ERROR utility.LogUtility (LogUtility.java:13) - execute<br/>ExecuteAction.java 58
http-8080-6 ERROR utility.LogUtility (LogUtility.java:14) -<br/>org.apache.struts.chain.commands.servlet.ExecuteAction.execute(ExecuteAction.java:58)
http-8080-6 ERROR utility.LogUtility (LogUtility.java:13) - execute<br/>AbstractExecuteAction.java 67
http-8080-6 ERROR utility.LogUtility (LogUtility.java:14) -<br/>org.apache.struts.chain.commands.AbstractExecuteAction.execute(AbstractExecuteAction.java:67)
http-8080-6 ERROR utility.LogUtility (LogUtility.java:13) - execute<br/>ActionCommandBase.java 51
http-8080-6 ERROR utility.LogUtility (LogUtility.java:14) -<br/>org.apache.struts.chain.commands.ActionCommandBase.execute(ActionCommandBase.java:51)
http-8080-6 ERROR utility.LogUtility (LogUtility.java:13) - execute<br/>ChainBase.java 191
http-8080-6 ERROR utility.LogUtility (LogUtility.java:14) -<br/>org.apache.commons.chain.impl.ChainBase.execute(ChainBase.java:191)
http-8080-6 ERROR utility.LogUtility (LogUtility.java:13) - execute<br/>LookupCommand.java 305
http-8080-6 ERROR utility.LogUtility (LogUtility.java:14) -<br/>org.apache.commons.chain.generic.LookupCommand.execute(LookupCommand.java:305)
http-8080-6 ERROR utility.LogUtility (LogUtility.java:13) - execute<br/>ChainBase.java 191
http-8080-6 ERROR utility.LogUtility (LogUtility.java:14) -<br/>org.apache.commons.chain.impl.ChainBase.execute(ChainBase.java:191)
http-8080-6 ERROR utility.LogUtility (LogUtility.java:13) - process<br/>ComposableRequestProcessor.java 283
http-8080-6 ERROR utility.LogUtility (LogUtility.java:14) -<br/>org.apache.struts.chain.ComposableRequestProcessor.process(ComposableRequestProcessor.java:283)
http-8080-6 ERROR utility.LogUtility (LogUtility.java:13) - process<br/>ActionServlet.java 1913
http-8080-6 ERROR utility.LogUtility (LogUtility.java:14) -<br/>org.apache.struts.action.ActionServlet.process(ActionServlet.java:1913)
http-8080-6 ERROR utility.LogUtility (LogUtility.java:13) - doPost<br/>ActionServlet.java 462
http-8080-6 ERROR utility.LogUtility (LogUtility.java:14) -<br/>org.apache.struts.action.ActionServlet.doPost(ActionServlet.java:462)
http-8080-6 ERROR utility.LogUtility (LogUtility.java:13) - service<br/>HttpServlet.java 710
http-8080-6 ERROR utility.LogUtility (LogUtility.java:14) -<br/>javax.servlet.http.HttpServlet.service(HttpServlet.java:710)
http-8080-6 ERROR utility.LogUtility (LogUtility.java:13) - service<br/>HttpServlet.java 803
http-8080-6 ERROR utility.LogUtility (LogUtility.java:14) -<br/>javax.servlet.http.HttpServlet.service(HttpServlet.java:803)
http-8080-6 ERROR utility.LogUtility (LogUtility.java:13) - internalDoFilter<br/>ApplicationFilterChain.java 290
http-8080-6 ERROR utility.LogUtility (LogUtility.java:14) -<br/>org.apache.catalina.core.ApplicationFilterChain.internalDoFilter(ApplicationFilterChain.java:290)
http-8080-6 ERROR utility.LogUtility (LogUtility.java:13) - doFilter<br/>ApplicationFilterChain.java 206
http-8080-6 ERROR utility.LogUtility (LogUtility.java:14) -<br/>org.apache.catalina.core.ApplicationFilterChain.doFilter(ApplicationFilterChain.java:206)
http-8080-6 ERROR utility.LogUtility (LogUtility.java:13) - invoke<br/>StandardWrapperValve.java 228
http-8080-6 ERROR utility.LogUtility (LogUtility.java:14) -<br/>org.apache.catalina.core.StandardWrapperValve.invoke(StandardWrapperValve.java:228)
http-8080-6 ERROR utility.LogUtility (LogUtility.java:13) - invoke<br/>StandardContextValve.java 175
http-8080-6 ERROR utility.LogUtility (LogUtility.java:14) -<br/>org.apache.catalina.core.StandardContextValve.invoke(StandardContextValve.java:175)
http-8080-6 ERROR utility.LogUtility (LogUtility.java:13) - invoke<br/>StandardHostValve.java 128
http-8080-6 ERROR utility.LogUtility (LogUtility.java:14) -<br/>org.apache.catalina.core.StandardHostValve.invoke(StandardHostValve.java:128)
http-8080-6 ERROR utility.LogUtility (LogUtility.java:13) - invoke<br/>ErrorReportValve.java 104
http-8080-6 ERROR utility.LogUtility (LogUtility.java:14) -<br/>org.apache.catalina.valves.ErrorReportValve.invoke(ErrorReportValve.java:104)
http-8080-6 ERROR utility.LogUtility (LogUtility.java:13) - invoke<br/>StandardEngineValve.java 109
http-8080-6 ERROR utility.LogUtility (LogUtility.java:14) -<br/>org.apache.catalina.core.StandardEngineValve.invoke(StandardEngineValve.java:109)
http-8080-6 ERROR utility.LogUtility (LogUtility.java:13) - service<br/>CoyoteAdapter.java 216
http-8080-6 ERROR utility.LogUtility (LogUtility.java:14) -<br/>org.apache.catalina.connector.CoyoteAdapter.service(CoyoteAdapter.java:216)
http-8080-6 ERROR utility.LogUtility (LogUtility.java:13) - process<br/>Http11Processor.java 844
http-8080-6 ERROR utility.LogUtility (LogUtility.java:14) -<br/>org.apache.coyote.http11.Http11Processor.process(Http11Processor.java:844)
http-8080-6 ERROR utility.LogUtility (LogUtility.java:13) - process<br/>Http11Protocol.java 634
http-8080-6 ERROR utility.LogUtility (LogUtility.java:14) -<br/>org.apache.coyote.http11.Http11Protocol$Http11ConnectionHandler.process(Http11Protocol.java:634)
http-8080-6 ERROR utility.LogUtility (LogUtility.java:13) - run<br/>JIoEndpoint.java 445
http-8080-6 ERROR utility.LogUtility (LogUtility.java:14) -<br/>org.apache.tomcat.util.net.JIoEndpoint$Worker.run(JIoEndpoint.java:445)
http-8080-6 ERROR utility.LogUtility (LogUtility.java:13) - run  Thread.java 595
http-8080-6 ERROR utility.LogUtility (LogUtility.java:14) -<br/>java.lang.Thread.run(Thread.java:595)
So please tell me why this exception occurs.
Thanking you..
Regards
Umesh
</quotepara></quote><footer type="noise" depth="0">
</footer><footer type="signature" depth="0" hash="16294502281639514258">--
This message is automatically generated by JIRA.
For more information on JIRA, see: <url>http://www.atlassian.com/software/jira</url>
</footer></body></message>