<message message-id="114151762.1152389062345.JavaMail.haus-jira@codehaus01.managed.contegix.com" list="org.apache.maven.issues" id="24cram77oldi2xee" type="bugs" date="2006-07-08T15:04:22-05:00" year="2006-01-01" year-month="2006-07-01" year-month-day="2006-07-08" thread-id="o3q566rhzz3kcwfh"><headers><envelope-from-line>From issues-return-7183-apmail-maven-issues-archive=maven.apache.org@maven.apache.org Sun Jul 09 02:49:11 2006</envelope-from-line><from personal="Mike Perham (JIRA)" address="jira@codehaus.org">"Mike Perham (JIRA)" &lt;jira@codehaus.org&gt;</from><to personal="issues@maven.apache.org" address="issues@maven.apache.org">issues@maven.apache.org</to><subject normal="[jira] Closed: (MINSTALL-24) Unable to install source or javadoc artifacts in local repository">[jira] Closed: (MINSTALL-24) Unable to install source or javadoc
 artifacts in local repository</subject><return-path>issues-return-7183-apmail-maven-issues-archive=maven.apache.org@maven.apache.org</return-path><delivered-to>apmail-maven-issues-archive@locus.apache.org</delivered-to><received>(qmail 40238 invoked from network); 9 Jul 2006 02:49:09 -0000</received><received>from hermes.apache.org (HELO mail.apache.org) (209.237.227.199)
  by minotaur.apache.org with SMTP; 9 Jul 2006 02:49:08 -0000</received><received>(qmail 39683 invoked by uid 500); 9 Jul 2006 02:48:16 -0000</received><delivered-to>apmail-maven-issues-archive@maven.apache.org</delivered-to><received>(qmail 38990 invoked by uid 500); 9 Jul 2006 02:48:13 -0000</received><mailing-list>contact issues-help@maven.apache.org; run by ezmlm</mailing-list><precedence>bulk</precedence><list-help>&lt;mailto:issues-help@maven.apache.org&gt;</list-help><list-unsubscribe>&lt;mailto:issues-unsubscribe@maven.apache.org&gt;</list-unsubscribe><list-post>&lt;mailto:issues@maven.apache.org&gt;</list-post><list-id>&lt;issues.maven.apache.org&gt;</list-id><reply-to>dev@maven.apache.org</reply-to><delivered-to>mailing list issues@maven.apache.org</delivered-to><received>(qmail 37268 invoked by uid 99); 9 Jul 2006 02:48:07 -0000</received><received>from asf.osuosl.org (HELO asf.osuosl.org) (140.211.166.49)
    by apache.org (qpsmtpd/0.29) with ESMTP; Sat, 08 Jul 2006 19:48:06 -0700</received><x-asf-spam-status>No, hits=0.5 required=10.0
	tests=DNS_FROM_RFC_ABUSE</x-asf-spam-status><x-spam-check-by>apache.org</x-spam-check-by><received-spf>neutral (asf.osuosl.org: local policy)</received-spf><received>from [63.246.20.114] (HELO 63-246-20-114.contegix.com) (63.246.20.114)
    by apache.org (qpsmtpd/0.29) with ESMTP; Sat, 08 Jul 2006 13:04:43 -0700</received><received>(qmail 9621 invoked by uid 89); 8 Jul 2006 20:04:22 -0000</received><received>from unknown (HELO codehaus01.managed.contegix.com) (127.0.0.1)
  by smtp.domain.com with SMTP; 8 Jul 2006 20:04:22 -0000</received><message-id>114151762.1152389062345.JavaMail.haus-jira@codehaus01.managed.contegix.com</message-id><date>Sat, 8 Jul 2006 15:04:22 -0500 (CDT)</date><in-reply-to>&lt;70437194.1150229322229.JavaMail.haus-jira@codehaus01.managed.contegix.com&gt;</in-reply-to><mime-version>1.0</mime-version><content-type>text/plain; charset=ISO-8859-1</content-type><content-transfer-encoding>7bit</content-transfer-encoding><x-virus-checked>Checked by ClamAV on apache.org</x-virus-checked><x-spam-rating>minotaur.apache.org 1.6.2 0/1000/N</x-spam-rating></headers><normalized-references><normalized-message-id>114151762.1152389062345.JavaMail.haus-jira@codehaus01.managed.contegix.com</normalized-message-id><normalized-in-reply-to>70437194.1150229322229.JavaMail.haus-jira@codehaus01.managed.contegix.com</normalized-in-reply-to></normalized-references><body type="text/plain; charset=iso-8859-1"><para depth="0">     [ <url>http://jira.codehaus.org/browse/MINSTALL-24?page=all</url> ]

</para><para depth="0">Mike Perham closed MINSTALL-24:
-------------------------------

</para><para depth="0">     Resolution: Fixed
    Fix Version: 2.2

</para><para depth="0">Fixed and added unit test.

</para><quote depth="1"><quotepara depth="1">Unable to install source or javadoc artifacts in local repository
-----------------------------------------------------------------

</quotepara><quotepara depth="1">         Key: MINSTALL-24
         URL: <url>http://jira.codehaus.org/browse/MINSTALL-24</url>
     Project: Maven 2.x Install Plugin
        Type: Bug
</quotepara></quote><para depth="0">
</para><quote depth="1"><quotepara depth="1">    Versions: 2.1
    Reporter: Chris Hagmann
    Assignee: Mike Perham
    Priority: Critical
     Fix For: 2.2
</quotepara></quote><para depth="0">
</para><quote depth="1"><quotepara depth="1">I couldn't find a way of installing a source archive or a javadoc archive in the<br/>local repository. Basically I'm missing the option to specify a classifier when <br/>invoking mvn install:install-file. As you can see in the output below it <br/>overwrites the main artifact (e.g. xmlc-base-2.2.9.jar) 
F:\downloads\xmlc-src-2.2.9\xmlc-src-2.2.9\xmlc\modules\xmlc\src&gt;mvn install:ins
tall-file -Dfile=xmlc-base-2.2.9-sources.jar -DgroupId=org.enhydra.xmlc -Dartifa
ctId=xmlc-base -Dversion=2.2.9 -Dclassifier=sources -Dpackaging=jar
[INFO] Scanning for projects...
[INFO] Searching repository for plugin with prefix: 'install'.
[INFO] -------------------------------------------------------------------------
---
[INFO] Building Maven Default Project
[INFO]    task-segment: [install:install-file] (aggregator-style)
[INFO] -------------------------------------------------------------------------
---
[INFO] [install:install-file]
[INFO] Installing F:\downloads\xmlc-src-2.2.9\xmlc-src-2.2.9\xmlc\modules\xmlc\s
rc\xmlc-base-2.2.9-sources.jar to C:\tools\maven\m2-repository\org\enhydra\xmlc\
xmlc-base\2.2.9\xmlc-base-2.2.9.jar
[INFO] -------------------------------------------------------------------------
---
[INFO] BUILD SUCCESSFUL
[INFO] -------------------------------------------------------------------------
---
[INFO] Total time: 1 second
[INFO] Finished at: Tue Jun 13 12:58:16 PDT 2006
[INFO] Final Memory: 2M/4M
[INFO] -------------------------------------------------------------------------
---
The exact same works when using the deploy plugin to install a source artifact <br/>in the remote repository, because that plugin accepts an optional classifier. 
</quotepara></quote><footer type="signature" hash="4099425730343590391" depth="0">
-- 
This message is automatically generated by JIRA.
-
If you think it was sent incorrectly contact one of the administrators:
   <url>http://jira.codehaus.org/secure/Administrators.jspa</url>
-
For more information on JIRA, see:
   <url>http://www.atlassian.com/software/jira</url>

</footer></body></message>