<message message-id="62F57C4DBBCBD745B2CD64DE43BBD3D601D1B97D@ala-mail10.corp.ad.wrs.com" list="org.eclipse.cdt-dev" id="24czdatqs554qtq3" type="development" date="2008-10-28T14:51:54-07:00" year="2008-01-01" year-month="2008-10-01" year-month-day="2008-10-28" thread-id="norqszuteaoqoabc"><headers><envelope-from-line>Tue Oct 28 13:52:01 2008</envelope-from-line><from personal="Schaefer, Doug" address="Doug.Schaefer@windriver.com">"Schaefer, Doug" &lt;Doug.Schaefer@windriver.com&gt;</from><to personal="CDT General developers list." address="cdt-dev@eclipse.org">"CDT General developers list." &lt;cdt-dev@eclipse.org&gt;</to><subject normal="[cdt-dev] debug - active build configuration changes during launch">RE: [cdt-dev] debug - active build configuration changes during launch</subject><received>from srv-117d-be06.markmail.marklogic.com ([172.19.8.66])
          by mail-1.a.markmail.int (JAMES SMTP Server 2.3.1) with SMTP ID 182
          for &lt;jerrod.oneal.barron@a.markmail.org&gt;;
          Tue, 28 Oct 2008 13:52:01 -0800 (GMT-08:00)</received><received>from mail.eclipse.org (slb-117n.markmail.marklogic.com [172.19.8.33])
	by mgw-2.public.markmail.int (Postfix) with ESMTP id C7F5A3B30249
	for &lt;jerrod.oneal.barron@a.markmail.org&gt;; Tue, 28 Oct 2008 14:51:37 -0700 (PDT)</received><received>from node5.eclipse.org (localhost [127.0.0.1])
	by mail.eclipse.org (Postfix) with ESMTP id C64C75A93B;
	Tue, 28 Oct 2008 17:51:59 -0400 (EDT)</received><x-original-to>cdt-dev@eclipse.org</x-original-to><delivered-to>cdt-dev@eclipse.org</delivered-to><received>from mail.wrs.com (mail.windriver.com [147.11.1.11])
	by mail.eclipse.org (Postfix) with SMTP id D23D246E7D
	for &lt;cdt-dev@eclipse.org&gt;; Tue, 28 Oct 2008 17:51:56 -0400 (EDT)</received><received>from ALA-MAIL03.corp.ad.wrs.com (ala-mail03 [147.11.57.144])
	by mail.wrs.com (8.13.6/8.13.6) with ESMTP id m9SLpujD022964
	for &lt;cdt-dev@eclipse.org&gt;; Tue, 28 Oct 2008 14:51:56 -0700 (PDT)</received><received>from ala-mail10.corp.ad.wrs.com ([147.11.57.155]) by
	ALA-MAIL03.corp.ad.wrs.com with Microsoft SMTPSVC(6.0.3790.1830); 
	Tue, 28 Oct 2008 14:51:56 -0700</received><x-mimeole>Produced By Microsoft Exchange V6.5</x-mimeole><content-class>urn:content-classes:message</content-class><mime-version>1.0</mime-version><content-type>text/plain;
	charset="us-ascii"</content-type><content-transfer-encoding>quoted-printable</content-transfer-encoding><date>Tue, 28 Oct 2008 14:51:54 -0700</date><message-id>62F57C4DBBCBD745B2CD64DE43BBD3D601D1B97D@ala-mail10.corp.ad.wrs.com</message-id><in-reply-to>&lt;62F57C4DBBCBD745B2CD64DE43BBD3D601D1B96E@ala-mail10.corp.ad.wrs.com&gt;</in-reply-to><x-ms-has-attach/><x-ms-tnef-correlator/><thread-topic>[cdt-dev] debug - active build configuration changes during
	launch</thread-topic><thread-index>Ack5RN+tU5kg9jFh3UaTmqkoDFCcCgAAaURAAAAT4vA=</thread-index><references>&lt;4907820B.8080502@qnx.com&gt; &lt;C52CEF71.542D0%ken.ryall@nokia.com&gt;
	&lt;62F57C4DBBCBD745B2CD64DE43BBD3D601D1B96E@ala-mail10.corp.ad.wrs.com&gt;</references><x-originalarrivaltime>28 Oct 2008 21:51:56.0681 (UTC)
	FILETIME=[6599CF90:01C93947]</x-originalarrivaltime><x-beenthere>cdt-dev@eclipse.org</x-beenthere><x-mailman-version>2.1.5</x-mailman-version><precedence>list</precedence><reply-to>"CDT General developers list." &lt;cdt-dev@eclipse.org&gt;</reply-to><list-id>"CDT General developers list." &lt;cdt-dev.eclipse.org&gt;</list-id><list-unsubscribe>&lt;https://dev.eclipse.org/mailman/listinfo/cdt-dev&gt;,
	&lt;mailto:cdt-dev-request@eclipse.org?subject=unsubscribe&gt;</list-unsubscribe><list-archive>&lt;https://dev.eclipse.org/mailman/private/cdt-dev&gt;</list-archive><list-post>&lt;mailto:cdt-dev@eclipse.org&gt;</list-post><list-help>&lt;mailto:cdt-dev-request@eclipse.org?subject=help&gt;</list-help><list-subscribe>&lt;https://dev.eclipse.org/mailman/listinfo/cdt-dev&gt;,
	&lt;mailto:cdt-dev-request@eclipse.org?subject=subscribe&gt;</list-subscribe><sender>cdt-dev-bounces@eclipse.org</sender><errors-to>cdt-dev-bounces@eclipse.org</errors-to></headers><normalized-references><normalized-message-id>62F57C4DBBCBD745B2CD64DE43BBD3D601D1B97D@ala-mail10.corp.ad.wrs.com</normalized-message-id><normalized-thread-index>Ack5RN+tU5kg9jFh3UaTmqkoDFCcCg</normalized-thread-index><normalized-in-reply-to>62F57C4DBBCBD745B2CD64DE43BBD3D601D1B96E@ala-mail10.corp.ad.wrs.com</normalized-in-reply-to><normalized-reference>4907820B.8080502@qnx.com</normalized-reference><normalized-reference>C52CEF71.542D0%ken.ryall@nokia.com</normalized-reference><normalized-reference>62F57C4DBBCBD745B2CD64DE43BBD3D601D1B96E@ala-mail10.corp.ad.wrs.com</normalized-reference></normalized-references><body type="text/plain;&#13;&#10;&#9;charset=&quot;us-ascii&quot;"><para depth="0">To add a little more detail on this quickly evolving feature ;), the
launchers can be aware of configurations, independend of the build
system, and you should be able to set a configuration per launch config.
We'd have to figure out the mechanism for how this configuration is set
and returned properly when the pre-launch build is done, but then that's
the root of the problem today...

</para><para depth="0">Doug.

</para><quote depth="1"><quotepara depth="1">-----Original Message-----
From: <email>cdt-dev-bounces@eclipse.org</email> 
[mailto:<email>cdt-dev-bounces@eclipse.org</email>] On Behalf Of Schaefer, Doug
Sent: Tuesday, October 28, 2008 5:47 PM
To: CDT General developers list.
Subject: RE: [cdt-dev] debug - active build configuration 
changes during launch

</quotepara><quotepara depth="1">For 6.0, I want to add configuration to the CModel. A project 
can have different active configurations for different 
purposes. We already have the concept of separate ones for 
build and indexing. If we want a separate one for launching, 
I think we can do that.

</quotepara><quotefooter type="signature" depth="1" hash="890217696831760888">Doug.

</quotefooter><quote depth="2"><quotepara depth="2">-----Original Message-----
From: <email>cdt-dev-bounces@eclipse.org</email>
[mailto:<email>cdt-dev-bounces@eclipse.org</email>] On Behalf Of Ken Ryall
Sent: Tuesday, October 28, 2008 5:34 PM
To: CDT General developers list.
Subject: Re: [cdt-dev] debug - active build configuration changes 
during launch

</quotepara><quotepara depth="2">I'm not completely sure but I think the first thing I'll do 
is add a 
setting so you can disable this feature completely.
Then I'll work on the other issues you mentioned.

</quotepara><quotefooter type="signature" depth="2" hash="17227647162257417728">- Ken

</quotefooter><quote depth="3"><quotepara depth="3">From: ext Elena Laskavaia &lt;<email>elaskavaia@qnx.com</email>&gt;
Organization: QNX
Reply-To: "CDT General developers list." &lt;<email>cdt-dev@eclipse.org</email>&gt;
Date: Tue, 28 Oct 2008 17:20:11 -0400
To: "CDT General developers list." &lt;<email>cdt-dev@eclipse.org</email>&gt;
Subject: Re: [cdt-dev] debug - active build configuration changes 
during launch

</quotepara><quotepara depth="3">Please describe how do you propose fixing it for 5.0.2?

</quotepara><quotepara depth="3">Ken Ryall wrote:
</quotepara><quote depth="4"><quotepara depth="4">Elena,

</quotepara><quotepara depth="4">I worked on this originally and I agree that it needs to
be improved
to handle the problems and use cases you mentioned. Please
don't remove it.
I'll work on some short term improvements for 5.0.2 and
more for 6.0.

</quotepara><quotefooter type="signature" depth="4" hash="17227647162257417728">- Ken

</quotefooter><quote depth="5"><quotepara depth="5">From: ext Elena Laskavaia &lt;<email>elaskavaia@qnx.com</email>&gt;
Organization: QNX
Reply-To: "CDT General developers list." &lt;<email>cdt-dev@eclipse.org</email>&gt;
Date: Tue, 28 Oct 2008 16:48:34 -0400
To: "CDT General developers list." &lt;<email>cdt-dev@eclipse.org</email>&gt;
Subject: [cdt-dev] debug - active build configuration
changes during
launch

</quotepara><quotepara depth="5">Regarding
<url>https://bugs.eclipse.org/bugs/show_bug.cgi?id=229740</url>

</quotepara><quotepara depth="5">We have a "feature" that launch config remembers first
active launch
configuration for managed projects and when it launches 
(if build 
when launch enabled) it is setting it to active and then builds.

</quotepara><quotepara depth="5">This is really bad, because
a) It does not restore active build config that was set 
by user, 
meaning my active config magically changes for unknown 
reason (I 
know why now...)
b) If user changes project in launch config this magical build 
config does not change, so if you lucky you have same
launch config
in this another project and it will build, if not you get an NPE
(bug236847 which is fixed on trunk by
somebody)
c) If user deletes related config same NPE
d) There is no user setting that allow to change or even
view config
associated with the launch
e) additionally if project is not managed project or not
intent to
be re-build when launching there is no way to specify it

</quotepara><quotepara depth="5">I will remove this functionality in 5.0.2 (i.e. setting active 
config to "launch" related build config when building, it
will build
user selected active config).
any objections?

</quotepara><quotepara depth="5">For 6.0 we should implement proper fix:
- support from UI
- support when build config is deleted
- support if different project is selected
- support for "none" as build config - that allow not to build 
project for this launch 
</quotepara><quotefooter type="list-management" depth="5">_______________________________________________
cdt-dev mailing list
<email>cdt-dev@eclipse.org</email>
<url>https://dev.eclipse.org/mailman/listinfo/cdt-dev</url>
</quotefooter></quote><quotefooter type="noise" depth="4">
</quotefooter><quotefooter type="list-management" depth="4">_______________________________________________
cdt-dev mailing list
<email>cdt-dev@eclipse.org</email>
<url>https://dev.eclipse.org/mailman/listinfo/cdt-dev</url>
</quotefooter></quote><quotefooter type="list-management" depth="3">_______________________________________________
cdt-dev mailing list
<email>cdt-dev@eclipse.org</email>
<url>https://dev.eclipse.org/mailman/listinfo/cdt-dev</url>
</quotefooter></quote><quotefooter type="noise" depth="2">
</quotefooter><quotefooter type="list-management" depth="2">_______________________________________________
cdt-dev mailing list
<email>cdt-dev@eclipse.org</email>
<url>https://dev.eclipse.org/mailman/listinfo/cdt-dev</url>

</quotefooter></quote><quotefooter type="list-management" depth="1">_______________________________________________
cdt-dev mailing list
<email>cdt-dev@eclipse.org</email>
<url>https://dev.eclipse.org/mailman/listinfo/cdt-dev</url>

</quotefooter></quote><footer type="list-management" depth="0">_______________________________________________
cdt-dev mailing list
<email>cdt-dev@eclipse.org</email>
<url>https://dev.eclipse.org/mailman/listinfo/cdt-dev</url>
</footer></body></message>